mwtextextractor/__init__.py
mwtextextractor/body.py
mwtextextractor-0.1.3.dist-info/METADATA
mwtextextractor-0.1.3.dist-info/RECORD
mwtextextractor-0.1.3.dist-info/WHEEL
mwtextextractor-0.1.3.dist-info/top_level.txt
