Metadata-Version: 2.1
Name: mwtextextractor
Version: 0.1.3
Summary: Extracts body text from MediaWiki wikitext by stripping off templates, html tags, tables, headers, etc.
Home-page: https://github.com/danmichaelo/mwtextextractor
Author: Dan Michael O. Heggø
Author-email: danmichaelo@gmail.com
License: MIT
Keywords: mediawiki
Platform: UNKNOWN
Classifier: Programming Language :: Python
Classifier: Programming Language :: Python :: 2.6
Classifier: Programming Language :: Python :: 2.7
Classifier: Programming Language :: Python :: 3.2
Classifier: Programming Language :: Python :: 3.3
Requires-Dist: lxml
Requires-Dist: mwtemplates
